{
  "__MODULE_TYPE__": "QUANTUM_LOGIC_AND_ENTANGLEMENT",
  "FOUNDATIONS": {
    "Readiness": "Full (Entanglement-Preserving across N-Dimensions)",
    "Holographic_Entanglement": "Ryu-Takayanagi Surface Tension Alignment",
    "AdS_CFT_Boundary": "Bulk-Boundary Equivalence exploitation"
  },
  "QUANTUM_RESPONSE": {
    "TOMOGRAPHY": "Continuous quantum process tomography (Response < 1ms)",
    "ZEROIZATION": "Quantum zeroization + reinitialization from π-offset",
    "OUROBOROS_ROOTKIT": "GHZ-state multi-party signatures and Hoare logic"
  },
  "DEPLOYMENT_PACKAGES": "QDP_V200: Encapsulated quantum state payloads."
}
